UART/Fifo.v
/////////////////////////////////////////////////////////
// This module is to create a Fifo inside the project. //
// The Fifo's data size and depth can be adjusted      //
// using the parameters, "DATA_SIZE" and "FIFO_SIZE"   //
// respectively.                                       //
/////////////////////////////////////////////////////////

`default_nettype none

// Main module for Fifo
module Fifo#(
	parameter DATA_SIZE = 8,
	parameter FIFO_SIZE = 8	// Fifo size
	)(
	// Power pins
	`ifdef USE_POWER_PINS
	inout vccd1,			// User area 1 1.8V supply
	inout vssd1,			// User area 1 digital ground
	`endif
	// Ports
	input wire clock,		// Main clk for fifo
	input wire reset_n,		// Master reset for fifo
	
	input wire data_inen,		// Data in flag
	input wire data_outen,		// Data out flag
	
	output wire fifo_empty,	// Fifo empty flag
	output wire fifo_full,		// Fifo full flag
	
	input wire [(DATA_SIZE-1):0] data_in,	// Data input to fifo
	output reg [(DATA_SIZE-1):0] data_out	// Data output from fifo
	);
	
	reg [($clog2(FIFO_SIZE) - 1) : 0] wptr;	// Write pointer
	reg [($clog2(FIFO_SIZE) - 1) : 0] rptr;	// Read pointer
	
	reg fifo_emptyreg;				// Fifo empty reg
	reg fifo_fullreg;				// Fifo full reg
	
	reg [(DATA_SIZE-1):0] memory [(FIFO_SIZE - 1):0];	// Memory for the fifo
	
	integer i = 0;					// temp variable
	
	assign fifo_empty = fifo_emptyreg;
	assign fifo_full = fifo_fullreg;
	
	initial begin
		wptr = 0;
		rptr = 0;
		
		fifo_emptyreg = 1'b1;
		fifo_fullreg  = 1'b0;
		
		data_out = {DATA_SIZE{1'b0}};
		
		for (i=0; i<FIFO_SIZE; i=i+1)
			memory[i] = 0;
	end
	
	always @ (posedge clock, negedge reset_n) begin
		if (~reset_n) begin	// reset everything
			wptr = 0;
			rptr = 0;
			
			fifo_emptyreg = 1'b1;
			fifo_fullreg  = 1'b0;
			
			data_out = {DATA_SIZE{1'b0}};
			
			for (i=0; i<FIFO_SIZE; i=i+1)
				memory[i] = 0;
		end
		else begin
			if ((~fifo_fullreg) & (data_inen)) begin
				memory[wptr] <= data_in;
				wptr <= wptr + 1;
				fifo_emptyreg <= 1'b0;
				
				if ((wptr+1'b1)==rptr)
					fifo_fullreg <= 1'b1;
				else
					fifo_fullreg <= 1'b0;
			end
			
			if ((~fifo_emptyreg) & (data_outen)) begin
				data_out <= memory[rptr];
				rptr <= rptr + 1;
				fifo_fullreg <= 1'b0;
				
				if ((rptr+1'b1)==wptr)
					fifo_emptyreg <= 1'b1;
				else
					fifo_emptyreg <= 1'b0;
			end
		end
	end

endmodule

`default_nettype wire

Fifo/Fifo_tb.v
/////////////////////////////////////////////////////////
// This module is to test the Fifo project. For more   //
// details, please refer the "FIFO.v" design file.     //
/////////////////////////////////////////////////////////

`default_nettype none

`timescale 10 ns / 1 ps

module Fifo_tb();

	reg clock;		// Main clk for fifo
	reg reset_n;		// Master reset for fifo
	
	reg data_inen;		// Data in flag
	reg data_outen;	// Data out flag
	
	wire fifo_empty;	// Fifo empty flag
	wire fifo_full;	// Fifo full flag
	
	reg [7:0] data_in;	// Data input to fifo
	wire [7:0] data_out;	// Data output from fifo
	
	Fifo #(.DATA_SIZE(16), .FIFO_SIZE(16))
	Fifo (.clock(clock), .reset_n(reset_n),
	      .data_inen(data_inen), .data_outen(data_outen),
	      .fifo_empty(fifo_empty), .fifo_full(fifo_full),
	      .data_in(data_in), .data_out(data_out));
	
	initial begin
		clock = 1'b0;
		reset_n = 1'b0;
		data_inen = 1'b0;
		data_outen = 1'b0;
		data_in = 8'd0;
	end
	
	always #1 clock <= ~clock;
	
	initial begin
		#100 reset_n = 1'b1;
		#10 data_in = 8'b11110000;
		#10 data_inen = 1'b1;
		#2 data_inen = 1'b0;
		#2 data_outen = 1'b1;
		#5 data_outen = 1'b0;
		#10 data_inen = 1'b1;
		#2 data_in = 8'd1;
		#2 data_in = 8'd2;
		#2 data_in = 8'd3;
		#2 data_in = 8'd4;
		#2 data_in = 8'd5;
		#2 data_in = 8'd6;
		#2 data_in = 8'd7;
		#2 data_in = 8'd8;
		#2 data_in = 8'd9;
		#2 data_in = 8'd10;
		#2 data_in = 8'd11;
		#2 data_in = 8'd12;
		#2 data_in = 8'd13;
		#2 data_in = 8'd14;
		#2 data_in = 8'd15;
		#2 data_in = 8'd16;
		#2 data_in = 8'd17;
		#2 data_in = 8'd18;
		#2 data_inen = 1'b0;
		#2 data_outen = 1'b1;
		#50 $display("All test cases finished!");
		$finish;
	end
	
	initial begin
		$dumpfile("Fifo_tb.vcd");
		$dumpvars(0, Fifo_tb);
		
		repeat(250) @(posedge clock);
		$display("Monitor: Timeout; Test failed...");
		$finish;
	end

endmodule

`default_nettype wire

Fifo/Fifo_tb.vcd
$date
	Thu Dec 22 22:59:19 2022
$end
$version
	Icarus Verilog
$end
$timescale
	1ps
$end
$scope module Fifo_tb $end
$var wire 1 ! fifo_full $end
$var wire 1 " fifo_empty $end
$var wire 8 # data_out [7:0] $end
$var reg 1 $ clock $end
$var reg 8 % data_in [7:0] $end
$var reg 1 & data_inen $end
$var reg 1 ' data_outen $end
$var reg 1 ( reset_n $end
$scope module Fifo $end
$var wire 1 $ clock $end
$var wire 8 ) data_in [7:0] $end
$var wire 1 & data_inen $end
$var wire 1 ' data_outen $end
$var wire 1 " fifo_empty $end
$var wire 1 ! fifo_full $end
$var wire 1 ( reset_n $end
$var reg 8 * data_out [7:0] $end
$var reg 1 + fifo_emptyreg $end
$var reg 1 , fifo_fullreg $end
$var reg 4 - rptr [3:0] $end
$var reg 4 . wptr [3:0] $end
$var integer 32 / i [31:0] $end
$upscope $end
$upscope $end
$enddefinitions $end
#0
$dumpvars
b10000 /
b0 .
b0 -
0,
1+
b0 *
b0 )
0(
0'
0&
b0 %
0$
b0 #
1"
0!
$end
#10000
b10000 /
1$
#20000
0$
#30000
b10000 /
1$
#40000
0$
#50000
b10000 /
1$
#60000
0$
#70000
b10000 /
1$
#80000
0$
#90000
b10000 /
1$
#100000
0$
#110000
b10000 /
1$
#120000
0$
#130000
b10000 /
1$
#140000
0$
#150000
b10000 /
1$
#160000
0$
#170000
b10000 /
1$
#180000
0$
#190000
b10000 /
1$
#200000
0$
#210000
b10000 /
1$
#220000
0$
#230000
b10000 /
1$
#240000
0$
#250000
b10000 /
1$
#260000
0$
#270000
b10000 /
1$
#280000
0$
#290000
b10000 /
1$
#300000
0$
#310000
b10000 /
1$
#320000
0$
#330000
b10000 /
1$
#340000
0$
#350000
b10000 /
1$
#360000
0$
#370000
b10000 /
1$
#380000
0$
#390000
b10000 /
1$
#400000
0$
#410000
b10000 /
1$
#420000
0$
#430000
b10000 /
1$
#440000
0$
#450000
b10000 /
1$
#460000
0$
#470000
b10000 /
1$
#480000
0$
#490000
b10000 /
1$
#500000
0$
#510000
b10000 /
1$
#520000
0$
#530000
b10000 /
1$
#540000
0$
#550000
b10000 /
1$
#560000
0$
#570000
b10000 /
1$
#580000
0$
#590000
b10000 /
1$
#600000
0$
#610000
b10000 /
1$
#620000
0$
#630000
b10000 /
1$
#640000
0$
#650000
b10000 /
1$
#660000
0$
#670000
b10000 /
1$
#680000
0$
#690000
b10000 /
1$
#700000
0$
#710000
b10000 /
1$
#720000
0$
#730000
b10000 /
1$
#740000
0$
#750000
b10000 /
1$
#760000
0$
#770000
b10000 /
1$
#780000
0$
#790000
b10000 /
1$
#800000
0$
#810000
b10000 /
1$
#820000
0$
#830000
b10000 /
1$
#840000
0$
#850000
b10000 /
1$
#860000
0$
#870000
b10000 /
1$
#880000
0$
#890000
b10000 /
1$
#900000
0$
#910000
b10000 /
1$
#920000
0$
#930000
b10000 /
1$
#940000
0$
#950000
b10000 /
1$
#960000
0$
#970000
b10000 /
1$
#980000
0$
#990000
b10000 /
1$
#1000000
0$
1(
#1010000
1$
#1020000
0$
#1030000
1$
#1040000
0$
#1050000
1$
#1060000
0$
#1070000
1$
#1080000
0$
#1090000
1$
#1100000
0$
b11110000 %
b11110000 )
#1110000
1$
#1120000
0$
#1130000
1$
#1140000
0$
#1150000
1$
#1160000
0$
#1170000
1$
#1180000
0$
#1190000
1$
#1200000
0$
1&
#1210000
0"
0+
b1 .
1$
#1220000
0$
0&
#1230000
1$
#1240000
0$
1'
#1250000
1"
1+
b1 -
b11110000 #
b11110000 *
1$
#1260000
0$
#1270000
1$
#1280000
0$
#1290000
1$
0'
#1300000
0$
#1310000
1$
#1320000
0$
#1330000
1$
#1340000
0$
#1350000
1$
#1360000
0$
#1370000
1$
#1380000
0$
#1390000
0"
0+
b10 .
1$
1&
#1400000
0$
#1410000
b11 .
1$
b1 %
b1 )
#1420000
0$
#1430000
b100 .
1$
b10 %
b10 )
#1440000
0$
#1450000
b101 .
1$
b11 %
b11 )
#1460000
0$
#1470000
b110 .
1$
b100 %
b100 )
#1480000
0$
#1490000
b111 .
1$
b101 %
b101 )
#1500000
0$
#1510000
b1000 .
1$
b110 %
b110 )
#1520000
0$
#1530000
b1001 .
1$
b111 %
b111 )
#1540000
0$
#1550000
b1010 .
1$
b1000 %
b1000 )
#1560000
0$
#1570000
b1011 .
1$
b1001 %
b1001 )
#1580000
0$
#1590000
b1100 .
1$
b1010 %
b1010 )
#1600000
0$
#1610000
b1101 .
1$
b1011 %
b1011 )
#1620000
0$
#1630000
b1110 .
1$
b1100 %
b1100 )
#1640000
0$
#1650000
b1111 .
1$
b1101 %
b1101 )
#1660000
0$
#1670000
b0 .
1$
b1110 %
b1110 )
#1680000
0$
#1690000
1!
1,
b1 .
1$
b1111 %
b1111 )
#1700000
0$
#1710000
1$
b10000 %
b10000 )
#1720000
0$
#1730000
1$
b10001 %
b10001 )
#1740000
0$
#1750000
1$
b10010 %
b10010 )
#1760000
0$
#1770000
1$
0&
#1780000
0$
#1790000
0!
0,
b10 -
1$
1'
#1800000
0$
#1810000
b11 -
b1 #
b1 *
1$
#1820000
0$
#1830000
b100 -
b10 #
b10 *
1$
#1840000
0$
#1850000
b101 -
b11 #
b11 *
1$
#1860000
0$
#1870000
b110 -
b100 #
b100 *
1$
#1880000
0$
#1890000
b111 -
b101 #
b101 *
1$
#1900000
0$
#1910000
b1000 -
b110 #
b110 *
1$
#1920000
0$
#1930000
b1001 -
b111 #
b111 *
1$
#1940000
0$
#1950000
b1010 -
b1000 #
b1000 *
1$
#1960000
0$
#1970000
b1011 -
b1001 #
b1001 *
1$
#1980000
0$
#1990000
b1100 -
b1010 #
b1010 *
1$
#2000000
0$
#2010000
b1101 -
b1011 #
b1011 *
1$
#2020000
0$
#2030000
b1110 -
b1100 #
b1100 *
1$
#2040000
0$
#2050000
b1111 -
b1101 #
b1101 *
1$
#2060000
0$
#2070000
b0 -
b1110 #
b1110 *
1$
#2080000
0$
#2090000
1"
1+
b1 -
b1111 #
b1111 *
1$
