Hack_Computer/Program_counter.v
/////////////////////////////////////////////////////////
// This module is to create a Program Counter inside   //
// the project. The co unter have variable data size   //
// that can be adjusted using the parameters           //
// "DATA_SIZE". It can be loaded, incremented or set   //
// to give the previous value.                         //
/////////////////////////////////////////////////////////

`default_nettype none

// Main module for Register
module Program_counter #(
	parameter DATA_SIZE = 16		// Data size of the register
	)(
	// Power pins
	`ifdef USE_POWER_PINS
	inout vccd1,				// User area 1 1.8V supply
	inout vssd1,				// User area 1 digital ground
	`endif
	// Ports
	input wire clock,			// Main clock
	input wire reset_n,			// Main reset_n
	
	
	input wire [(DATA_SIZE-1):0] in,	// Input data
	output reg [(DATA_SIZE-1):0] out,	// Output data
	
	input wire inc,			// Increment operation
	input wire load			// Load operation
	);
	
	initial begin
		out = {DATA_SIZE{1'b0}};
	end
	
	always @(posedge clock, negedge reset_n) begin
		if (~reset_n)
			out <= 0;
		else begin
			if (load)
				out <= in;
			else if (inc)
				out <= out + 1;
			else
				out <= out;
		end
	end
	
endmodule

`default_nettype wire

Hack_Computer/ALU.v
/////////////////////////////////////////////////////////
// This module is to create the ALU of the computer.   //
// The ALU takes two variables x and y, along with six //
// operations to produce output and two flags.         //
/////////////////////////////////////////////////////////

`default_nettype none

// Main module for ALU
module ALU(
	// Power pins
	`ifdef USE_POWER_PINS
	inout vccd1,			// User area 1 1.8V supply
	inout vssd1,			// User area 1 digital ground
	`endif
	// Ports
	 input wire	[15:0]    x,	// Variable x
	 input wire	[15:0]    y,	// Variable y
	 
	 input wire              zx,	// zero the x input?
	 input wire              nx,	// negate the x input?
	 input wire              zy,	// zero the y input?
	 input wire              ny,	// negate the y input?
	 input wire              f,	// compute out = f ? (x + y) : (x & y)
	 input wire              no,	// negate the out output?
	 
	 output wire	[15:0]    out,	// Result out
	 
	 output wire             zr,	// 1 iff out == 0
	 output wire             ng	// 1 iff out < 0
	);

	wire [15:0] x1;
	wire [15:0] x1not;
	wire [15:0] x2;
	wire [15:0] y1;
	wire [15:0] y1not;
	wire [15:0] y2;
	wire [15:0] sum;
	wire [15:0] x2andy2;
	wire [15:0] out0;
	wire [15:0] out0not;
	wire [15:0] outtmp;

	wire        outor0;
	wire        outor1;
	wire        outor;

	assign x1      = zx ? 16'd0 : x;
	assign x1not   = ~x1;
	assign x2      = nx ? x1not : x1;
	assign y1      = zy ? 16'd0 : y;
	assign y1not   = ~y1;
	assign y2      = ny ? y1not : y1;
	assign sum     = x2 + y2;
	assign x2andy2 = x2 & y2;
	assign out0    = f ? sum : x2andy2;
	assign out0not = ~out0;
	assign out     = no ? out0not : out0;
	assign outtmp  = out;

	assign outor0  = |outtmp[7:0];
	assign outor1  = |outtmp[15:8];
	assign outor   = outor0 | outor1;
	assign zr      = ~outor;
	assign ng      = outtmp[15] | 1'b0;

endmodule

`default_nettype wire

Hack_Computer/Register.v
/////////////////////////////////////////////////////////
// This module is to create a Register inside the      //
// Project. The Register have variable data size that  //
// can be adjusted using the parameters "DATA_SIZE".   //
/////////////////////////////////////////////////////////

`default_nettype none

// Main module for Register
module Register #(
	parameter DATA_SIZE = 16		// Data size of the register
	)(
	// Power pins
	`ifdef USE_POWER_PINS
	inout vccd1,				// User area 1 1.8V supply
	inout vssd1,				// User area 1 digital ground
	`endif
	// Ports
	input wire clock,			// Main clock
	
	input wire [(DATA_SIZE-1):0] in,	// Input data
	output reg [(DATA_SIZE-1):0] out,	// Output data
	
	input wire load			// Load operation
	);
	
	initial
		out = {DATA_SIZE{1'b0}};
		
	always @(posedge clock)
		out <= load ? in : out;

endmodule

`default_nettype wire

Hack_Computer/CPU.v
/////////////////////////////////////////////////////////
// This module is to create the CPU of the computer.   //
// The CPU takes in instruction and compute it using   //
// ALU, registers, program counter, memory and finally //
// takes the resultant data to it's desired location.  //
/////////////////////////////////////////////////////////

`default_nettype none

// Main module for CPU
module CPU(
	// Power pins
	`ifdef USE_POWER_PINS
	inout vccd1,				// User area 1 1.8V supply
	inout vssd1,				// User area 1 digital ground
	`endif
	// Ports
	input wire		clock,		// Main input clock
	input wire		reset_n,	// Main reset_n
	 
	input wire	[15:0]	inM,		// Input from memory
	input wire	[15:0]	instruction,	// Input instruction
	 
	output wire	[15:0]	outM,		// Output from memory
	output wire		writeM,	// Write to memory flag
	output wire	[14:0]	addressM,	// Memory address
	
	output wire	[14:0]	pc		// Output of program counter
	);
	
	wire [15:0] ALUOP;
	wire [15:0] AR;
	wire [15:0] ALU0;
	wire        zr;
	wire        ng;
	wire        loadnot;

	wire        ins15not;
	wire        aload0;
	wire        aload;
	wire        dload;
	wire        muxsel;
	wire [15:0] Aregister;
	wire [15:0] ALU1;

	wire        j3not;
	wire        j2not;
	wire        j1not;
	wire        zrnot;
	wire        ngnot;

	wire        j1j2;
	wire        j315;
	wire        inc0;
	wire        incre0;
	wire        inc;

	wire        le0;
	wire        l0;
	wire        l1;
	wire        g0;
	wire        j1notj3;
	wire        l2;
	wire        j1j3;
	wire        l3;
	wire        jmp0;
	wire        jmp1;
	wire        l4;

	wire        jmpcon0;
	wire        jmpcon1;
	wire        jmpcon;

	wire        load0;
	wire        load;

	wire [15:0] pctmp;
	
	
	assign  ins15not   = ~instruction[15];
	assign  aload0     = instruction[15] & instruction[5];
	assign  aload      = aload0 | ins15not;
	assign  dload      = instruction[15] & instruction[4];
	assign  muxsel     = instruction[15] & instruction[12];
	assign  writeM     = instruction[15] & instruction[3];
	assign  Aregister  = instruction[15] ? ALUOP : instruction;
	assign  ALU1       = muxsel ? inM : AR;
	assign  addressM   = AR[14:0];
	assign  outM       = ALUOP;
	
	assign  j3not      = ~instruction[0];
	assign  j2not      = ~instruction[1];
	assign  j1not      = ~instruction[2];
	assign  zrnot      = ~zr;
	assign  ngnot      = ~ng;

	assign  j1j2       = j1not & j2not;
	assign  j315       = j3not & instruction[15];
	assign  inc0       = j1j2 & j315;
	assign  incre0     = inc0 | ins15not;
	assign  inc        = incre0 | loadnot;		// PC inc

	assign  le0        = instruction[2] & ng;
	assign  l0         = le0 & j3not;			// OP < 0

	assign  l1         = zr & instruction[1];		// OP == 0

	assign  g0         = zrnot & ngnot;
	assign  j1notj3    = j1not & instruction[0];
	assign  l2         = j1notj3 & g0;			// OP > 0

	assign  j1j3       = instruction[2] & instruction[0];
	assign  l3         = j1j3 & zrnot;			// OP != 0

	assign  jmp0       = instruction[15] & instruction[2];
	assign  jmp1       = instruction[1] & instruction[0];
	assign  l4         = jmp0 & jmp1;			// JMP

	assign  jmpcon0    = instruction[0] | instruction[1];
	assign  jmpcon1    = jmpcon0 | instruction[2];
	assign  jmpcon     = jmpcon1 & instruction[15];

	assign  load0      = l0 | l1 | l2 | l3 | l4;
	assign  load       = load0 & jmpcon;
	assign  loadnot    = ~load;
	
	assign pc          = pctmp[14:0];

	Register ARegister (.clock(clock), .in(Aregister), 
			    .load(aload), .out(AR));
	Register DRegister (.clock(clock), .in(ALUOP), 
			    .load(dload), .out(ALU0));
	ALU 	 ALU       (.x(ALU0), .y(ALU1), 
			    .zx(instruction[11]), .nx(instruction[10]), 
			    .zy(instruction[9]), .ny(instruction[8]), 
			    .f(instruction[7]), .no(instruction[6]), 
			    .zr(zr), .ng(ng), .out(ALUOP));
	Program_counter PC0 (.clock(clock), .reset_n(reset_n), .in(AR), 
			    .load(load), .inc(inc), .out(pctmp));


endmodule

`default_nettype wire

Final/SRAM.v
/////////////////////////////////////////////////////////
// This module is to create a SRAM inside the project. //
// The SRAM have variable data size depth that can be  //
// adjusted using the parameters "DATA_SIZE" and       //
// "SRAM_DEPTH_LOG2" respectively. It is 1R1W SRAM.    //
// Both operations can work parallely but take care of //
// data coherency.                                     //
/////////////////////////////////////////////////////////

`default_nettype none

// Main module for SRAM
module SRAM #(
	parameter DATA_SIZE = 16,			// SRAM data size
	parameter SRAM_DEPTH_LOG2 = 5,		// SRAM address size
	parameter SRAM_DEPTH = 2**SRAM_DEPTH_LOG2	// SRAM depth
	)(
	// Power pins
	`ifdef USE_POWER_PINS
	inout vccd1,			// User area 1 1.8V supply
	inout vssd1,			// User area 1 digital ground
	`endif
	// Ports
	input wire clock,		// Main clk for sram
	input wire reset_n,		// Master reset for sram
	
	input wire data_rden,		// Data read flag
	input wire data_wren,		// Data write flag
	
	input wire [(DATA_SIZE-1):0] data_in,	 // Data input to sram
	output reg [(DATA_SIZE-1):0] data_out, // Data output from sram
	
	input wire [(SRAM_DEPTH_LOG2 - 1):0] addr_in,	 // Input data address
	input wire [(SRAM_DEPTH_LOG2 - 1):0] addr_out, // Output data address
	
	output wire sram_full		// High when addr_in is max.
	);
	
	reg [(DATA_SIZE-1):0] memory [(SRAM_DEPTH-1):0];	// Main memory
	
	integer i = 0;	// temp variable
	
	assign sram_full = &addr_in;
	
	initial begin
		data_out = {DATA_SIZE{1'b0}};
		
		for (i=0; i<SRAM_DEPTH; i=i+1)
			memory[i] = 0;
	end
	
	always @ (posedge clock, negedge reset_n) begin
		if (~reset_n) begin	// reset everything
			data_out = {DATA_SIZE{1'b0}};
		
			for (i=0; i<SRAM_DEPTH; i=i+1)
				memory[i] = 0;
		end
		else begin
			if (data_wren)
				memory[addr_in] <= data_in;
			
			if (data_rden)
				data_out <= memory[addr_out];
			
		end
	end

endmodule

`default_nettype wire

Hack_Computer/HACK_comp.v
/////////////////////////////////////////////////////////
// This module is the top module of HACK computer.     //
// Here CPU, data memory and instruction memory are    //
// integrated. Different clocks are provided to memory //
// and the CPU to have data integrity.                 //
/////////////////////////////////////////////////////////

`default_nettype none

// Main module for HACK_comp
module HACK_comp(
	// Power pins
	`ifdef USE_POWER_PINS
	inout vccd1,			// User area 1 1.8V supply
	inout vssd1,			// User area 1 digital ground
	`endif
	// Ports
	input wire	clock,		// Main clock for the system
	input wire	reset_n,	// Main reset for the system
	input wire	mem_clr_n,	// Reset for memory
	
	input wire	write_ins,	// Write into instruction memory
	//input wire	read_ins,	// Read from instruction memory
	input wire	write_data,	// Write into data memory
	input wire	read_data,	// Read from data memory
	
	input wire [15:0] addr_ins,	// Instruction memory address
	input wire [15:0] dati_ins,	// Data into instruction memory
	//output wire [15:0] dato_ins,	// Data from instruction memory
	
	input wire [15:0] addr_data,	// Data memory address
	input wire [15:0] dati_data,	// Data into Data memory
	output wire [15:0] dato_data,	// Data from Data memory
	
	output wire	data_memfull,	// Data memory full flag
	output wire	ins_memfull	// Instruction memory full flag
	);
	
	reg clock_cpu;	// Clock for the CPU
	
	wire [14:0] pc;
	wire [15:0] instruction;
	
	wire writeM;
	wire [14:0] addressM;
	wire [15:0] outM;
	wire [15:0] inM;
	
	// Data memory ports
	wire data_rden;
	wire data_wren;
	wire [15:0] data_in;
	wire [15:0] data_out;
	wire [14:0] dati_addr;
	wire [14:0] dato_addr;
	
	// Instruction memory ports
	wire inst_rden;
	wire inst_wren;
	wire [15:0] inst_in;
	wire [15:0] inst_out;
	wire [14:0] insi_addr;
	wire [14:0] inso_addr;
	
	
	SRAM #(.DATA_SIZE(16), .SRAM_DEPTH_LOG2(15))
	ins_mem0 (.clock(clock), .reset_n(mem_clr_n),
		  .data_rden(inst_rden), .data_wren(inst_wren),
		  .data_in(inst_in), .data_out(inst_out),
		  .addr_in(insi_addr), .addr_out(inso_addr),
		  .sram_full(ins_memfull));
	
	SRAM #(.DATA_SIZE(16), .SRAM_DEPTH_LOG2(15))
	dat_mem0 (.clock(clock), .reset_n(mem_clr_n),
		  .data_rden(data_rden), .data_wren(data_wren),
		  .data_in(data_in), .data_out(data_out),
		  .addr_in(dati_addr), .addr_out(dato_addr),
		  .sram_full(data_memfull));
	
	CPU CPU0 (.clock(clock_cpu), .reset_n(reset_n),
		  .inM(inM), .instruction(instruction),
		  .outM(outM), .writeM(writeM),
		  .addressM(addressM), .pc(pc));
	
	assign data_rden = 1'b1;
	assign data_wren = write_data ? 1'b1 : writeM;
	assign dati_addr = write_data ? addr_data[14:0] : addressM;
	assign dato_addr = read_data ? addr_data[14:0] : addressM;
	assign data_in = write_data ? dati_data : outM;
	assign dato_data = data_out;
	assign inM = data_out;
	
	assign inst_rden = 1'b1;
	assign inst_wren = write_ins ? 1'b1 : 1'b0;
	assign insi_addr = addr_ins[14:0];
	assign inso_addr = pc;
	//assign inso_addr = read_ins ? addr_ins[14:0] : pc;
	assign inst_in = dati_ins;
	assign instruction = inst_out;
	//assign dato_ins = inst_out;
		  
	initial begin
		clock_cpu = 1'b0;
	end
	
	always @(posedge clock, negedge reset_n) begin
		if (~reset_n)
			clock_cpu <= 1'b0;
		else
			clock_cpu <= ~clock_cpu;
	end
	
endmodule

`default_nettype wire

Hack_Computer/HACK_comp_tb.v
/////////////////////////////////////////////////////////
// This module is to test the HACK Computer project.   //
// For more details, please refer the "HACK_comp.v"    //
// design file.                                        //
/////////////////////////////////////////////////////////

`default_nettype none

`timescale 10 ns / 1 ps

module HACK_comp_tb();
	
	reg	clock;		// Main clock for the system
	reg	reset_n;	// Main reset for the system
	reg	mem_clr_n;	// Reset for memory
	
	reg	write_ins;	// Write into instruction memory
	//reg	read_ins;	// Read from instruction memory
	reg	write_data;	// Write into data memory
	reg	read_data;	// Read from data memory
	
	reg [15:0] addr_ins;	// Instruction memory address
	reg [15:0] dati_ins;	// Data into instruction memory
	//wire  [15:0] dato_ins;	// Data from instruction memory
	
	reg [15:0] addr_data;	// Data memory address
	reg [15:0] dati_data;	// Data into Data memory
	wire [15:0] dato_data;	// Data from Data memory
	
	wire	data_memfull;	// Data memory full flag
	wire	ins_memfull;	// Instruction memory full flag
	
	HACK_comp comp0 (.clock(clock), .reset_n(reset_n), .mem_clr_n(mem_clr_n),
			 .write_ins(write_ins), //.read_ins(read_ins),
			 .write_data(write_data), .read_data(read_data),
			 .addr_ins(addr_ins), .dati_ins(dati_ins),
			 //.dato_ins(dato_ins), 
			 .addr_data(addr_data),
			 .dati_data(dati_data), .dato_data(dato_data),
			 .data_memfull(data_memfull), .ins_memfull(ins_memfull));
	
	initial begin
		clock = 1'b0;
		reset_n = 1'b0;
		mem_clr_n = 1'b0;
		
		write_ins = 1'b0;
		//read_ins = 1'b0;
		write_data = 1'b0;
		read_data = 1'b0;
		
		addr_ins = 16'd0;
		dati_ins = 16'd0;
		addr_data = 16'd0;
		dati_data = 16'd0;
	end
	
	always #1 clock <= ~clock;
	
	initial begin
	
		#2 mem_clr_n = 1'b1;
		// Find max. of two numbers from Mem[0] and Mem[1]
		// Save max in Mem[2]
		#2 write_ins = 1'b1;			// Write instructions
		#2 addr_ins = 16'd0;			// Address
		#2 dati_ins = 16'b0000000000000000;	// Instruction
		#2 addr_ins = 16'd1;			// Address
		#2 dati_ins = 16'b1111110000010000;	// Instruction
		#2 addr_ins = 16'd2;			// Address
		#2 dati_ins = 16'b0000000000000001;	// Instruction
		#2 addr_ins = 16'd3;			// Address
		#2 dati_ins = 16'b1111010011010000;	// Instruction
		#2 addr_ins = 16'd4;			// Address
		#2 dati_ins = 16'b0000000000001010;	// Instruction
		#2 addr_ins = 16'd5;			// Address
		#2 dati_ins = 16'b1110001100000001;	// Instruction
		#2 addr_ins = 16'd6;			// Address
		#2 dati_ins = 16'b0000000000000001;	// Instruction
		#2 addr_ins = 16'd7;			// Address
		#2 dati_ins = 16'b1111110000010000;	// Instruction
		#2 addr_ins = 16'd8;			// Address
		#2 dati_ins = 16'b0000000000001100;	// Instruction
		#2 addr_ins = 16'd9;			// Address
		#2 dati_ins = 16'b1110101010000111;	// Instruction
		#2 addr_ins = 16'd10;			// Address
		#2 dati_ins = 16'b0000000000000000;	// Instruction
		#2 addr_ins = 16'd11;			// Address
		#2 dati_ins = 16'b1111110000010000;	// Instruction
		#2 addr_ins = 16'd12;			// Address
		#2 dati_ins = 16'b0000000000000010;	// Instruction
		#2 addr_ins = 16'd13;			// Address
		#2 dati_ins = 16'b1110001100001000;	// Instruction
		#2 addr_ins = 16'd14;			// Address
		#2 dati_ins = 16'b0000000000001110;	// Instruction
		#2 addr_ins = 16'd15;			// Address
		#2 dati_ins = 16'b1110101010000111;	// Instruction
		#2 write_ins = 1'b0;			// Instruction ends
		
		#2 write_data = 1'b1;			// Write data
		#2 addr_data = 16'd0;			// Address 0
		#2 dati_data = 16'd14;			// M[0]=14
		#2 addr_data = 16'd1;			// Address 1
		#2 dati_data = 16'd20;			// M[1]=20
		#2 write_data = 1'b0;			// Data ends
		
		#2 reset_n = 1'b1;			// Run code
		#50 read_data = 1'b1;			// Read data
		#2 addr_data = 16'd2;			// Address 2
		#2 $display(dato_data);		// Data
		#2 read_data = 1'b0;			// Read data ends
		if (dato_data == 16'd20)
			$display("All test cases passed!");
		else
			$display("Test failed!");
		$finish;
	
	/*
		#2 mem_clr_n = 1'b1;
		// Add number 5 and 10 and put them in RAM[0]
		#2 write_ins = 1'b1;			// Write instructions
		#2 addr_ins = 16'd0;			// Address
		#2 dati_ins = 16'b0000000000000101;	// Instruction
		#2 addr_ins = 16'd1;			// Address
		#2 dati_ins = 16'b1110110000010000;	// Instruction
		#2 addr_ins = 16'd2;			// Address
		#2 dati_ins = 16'b0000000000001010;	// Instruction
		#2 addr_ins = 16'd3;			// Address
		#2 dati_ins = 16'b1110000010010000;	// Instruction
		#2 addr_ins = 16'd4;			// Address
		#2 dati_ins = 16'b0000000000000000;	// Instruction
		#2 addr_ins = 16'd5;			// Address
		#2 dati_ins = 16'b1110001100001000;	// Instruction
		#2 write_ins = 1'b0;			// Instruction ends
		
		#2 reset_n = 1'b1;			// Run code
		#50 read_data = 1'b1;			// Read data
		#2 addr_data = 16'd0;			// Address 0
		#2 $display(dato_data);		// Data
		#2 read_data = 1'b0;			// Read data ends
		if (dato_data == 16'd15)
			$display("All test cases passed!");
		else
			$display("Test failed!");
		$finish;
	*/
	end
	
	initial begin
		$dumpfile("HACK_comp_tb.vcd");
		$dumpvars(0, HACK_comp_tb);
		
		repeat(300) @(posedge clock);
		$display("Monitor: Timeout; Test failed...");
		$finish;
	end
	
endmodule

`default_nettype wire

Hack_Computer/HACK_comp_tb.vcd
$date
	Tue Dec 27 23:59:37 2022
$end
$version
	Icarus Verilog
$end
$timescale
	1ps
$end
$scope module HACK_comp_tb $end
$var wire 1 ! ins_memfull $end
$var wire 16 " dato_data [15:0] $end
$var wire 1 # data_memfull $end
$var reg 16 $ addr_data [15:0] $end
$var reg 16 % addr_ins [15:0] $end
$var reg 1 & clock $end
$var reg 16 ' dati_data [15:0] $end
$var reg 16 ( dati_ins [15:0] $end
$var reg 1 ) mem_clr_n $end
$var reg 1 * read_data $end
$var reg 1 + reset_n $end
$var reg 1 , write_data $end
$var reg 1 - write_ins $end
$scope module comp0 $end
$var wire 16 . addr_data [15:0] $end
$var wire 16 / addr_ins [15:0] $end
$var wire 1 & clock $end
$var wire 1 0 data_rden $end
$var wire 16 1 dati_data [15:0] $end
$var wire 16 2 dati_ins [15:0] $end
$var wire 16 3 dato_data [15:0] $end
$var wire 16 4 inM [15:0] $end
$var wire 15 5 inso_addr [14:0] $end
$var wire 16 6 inst_in [15:0] $end
$var wire 1 7 inst_rden $end
$var wire 16 8 instruction [15:0] $end
$var wire 1 ) mem_clr_n $end
$var wire 1 * read_data $end
$var wire 1 + reset_n $end
$var wire 1 , write_data $end
$var wire 1 - write_ins $end
$var wire 1 9 writeM $end
$var wire 15 : pc [14:0] $end
$var wire 16 ; outM [15:0] $end
$var wire 1 < inst_wren $end
$var wire 16 = inst_out [15:0] $end
$var wire 15 > insi_addr [14:0] $end
$var wire 1 ! ins_memfull $end
$var wire 15 ? dato_addr [14:0] $end
$var wire 15 @ dati_addr [14:0] $end
$var wire 1 A data_wren $end
$var wire 16 B data_out [15:0] $end
$var wire 1 # data_memfull $end
$var wire 16 C data_in [15:0] $end
$var wire 15 D addressM [14:0] $end
$var reg 1 E clock_cpu $end
$scope module CPU0 $end
$var wire 1 F aload $end
$var wire 1 G aload0 $end
$var wire 1 E clock $end
$var wire 1 H dload $end
$var wire 1 I g0 $end
$var wire 16 J inM [15:0] $end
$var wire 1 K inc $end
$var wire 1 L inc0 $end
$var wire 1 M incre0 $end
$var wire 1 N ins15not $end
$var wire 16 O instruction [15:0] $end
$var wire 1 P j1j2 $end
$var wire 1 Q j1j3 $end
$var wire 1 R j1not $end
$var wire 1 S j1notj3 $end
$var wire 1 T j2not $end
$var wire 1 U j315 $end
$var wire 1 V j3not $end
$var wire 1 W jmp0 $end
$var wire 1 X jmp1 $end
$var wire 1 Y jmpcon $end
$var wire 1 Z jmpcon0 $end
$var wire 1 [ jmpcon1 $end
$var wire 1 \ l0 $end
$var wire 1 ] l1 $end
$var wire 1 ^ l2 $end
$var wire 1 _ l3 $end
$var wire 1 ` l4 $end
$var wire 1 a le0 $end
$var wire 1 b load $end
$var wire 1 c load0 $end
$var wire 1 d loadnot $end
$var wire 1 e muxsel $end
$var wire 1 f ngnot $end
$var wire 16 g outM [15:0] $end
$var wire 1 + reset_n $end
$var wire 1 9 writeM $end
$var wire 1 h zrnot $end
$var wire 1 i zr $end
$var wire 16 j pctmp [15:0] $end
$var wire 15 k pc [14:0] $end
$var wire 1 l ng $end
$var wire 15 m addressM [14:0] $end
$var wire 16 n Aregister [15:0] $end
$var wire 16 o AR [15:0] $end
$var wire 16 p ALUOP [15:0] $end
$var wire 16 q ALU1 [15:0] $end
$var wire 16 r ALU0 [15:0] $end
$scope module ALU $end
$var wire 1 s f $end
$var wire 1 l ng $end
$var wire 1 t no $end
$var wire 1 u nx $end
$var wire 1 v ny $end
$var wire 16 w out0not [15:0] $end
$var wire 1 x outor $end
$var wire 16 y outtmp [15:0] $end
$var wire 16 z x1not [15:0] $end
$var wire 16 { x2andy2 [15:0] $end
$var wire 16 | y [15:0] $end
$var wire 16 } y1not [15:0] $end
$var wire 1 i zr $end
$var wire 1 ~ zx $end
$var wire 1 !" zy $end
$var wire 16 "" y2 [15:0] $end
$var wire 16 #" y1 [15:0] $end
$var wire 16 $" x2 [15:0] $end
$var wire 16 %" x1 [15:0] $end
$var wire 16 &" x [15:0] $end
$var wire 16 '" sum [15:0] $end
$var wire 1 (" outor1 $end
$var wire 1 )" outor0 $end
$var wire 16 *" out0 [15:0] $end
$var wire 16 +" out [15:0] $end
$upscope $end
$scope module ARegister $end
$var wire 1 E clock $end
$var wire 16 ," in [15:0] $end
$var wire 1 F load $end
$var reg 16 -" out [15:0] $end
$upscope $end
$scope module DRegister $end
$var wire 1 E clock $end
$var wire 16 ." in [15:0] $end
$var wire 1 H load $end
$var reg 16 /" out [15:0] $end
$upscope $end
$scope module PC0 $end
$var wire 1 E clock $end
$var wire 16 0" in [15:0] $end
$var wire 1 K inc $end
$var wire 1 b load $end
$var wire 1 + reset_n $end
$var reg 16 1" out [15:0] $end
$upscope $end
$upscope $end
$scope module dat_mem0 $end
$var wire 15 2" addr_in [14:0] $end
$var wire 15 3" addr_out [14:0] $end
$var wire 1 & clock $end
$var wire 16 4" data_in [15:0] $end
$var wire 1 0 data_rden $end
$var wire 1 A data_wren $end
$var wire 1 ) reset_n $end
$var wire 1 # sram_full $end
$var reg 16 5" data_out [15:0] $end
$var integer 32 6" i [31:0] $end
$upscope $end
$scope module ins_mem0 $end
$var wire 15 7" addr_in [14:0] $end
$var wire 15 8" addr_out [14:0] $end
$var wire 1 & clock $end
$var wire 16 9" data_in [15:0] $end
$var wire 1 7 data_rden $end
$var wire 1 < data_wren $end
$var wire 1 ) reset_n $end
$var wire 1 ! sram_full $end
$var reg 16 :" data_out [15:0] $end
$var integer 32 ;" i [31:0] $end
$upscope $end
$upscope $end
$upscope $end
$enddefinitions $end
#0
$dumpvars
b1000000000000000 ;"
b0 :"
b0 9"
b0 8"
b0 7"
b1000000000000000 6"
b0 5"
b0 4"
b0 3"
b0 2"
b0 1"
b0 0"
b0 /"
b0 ."
b0 -"
b0 ,"
b0 +"
b0 *"
0)"
0("
b0 '"
b0 &"
b0 %"
b0 $"
b0 #"
b0 ""
0!"
0~
b1111111111111111 }
b0 |
b0 {
b1111111111111111 z
b0 y
0x
b1111111111111111 w
0v
0u
0t
0s
b0 r
b0 q
b0 p
b0 o
b0 n
b0 m
0l
b0 k
b0 j
1i
0h
b0 g
1f
0e
1d
0c
0b
0a
0`
0_
0^
0]
0\
0[
0Z
0Y
0X
0W
1V
0U
1T
0S
1R
0Q
1P
b0 O
1N
1M
0L
1K
b0 J
0I
0H
0G
1F
0E
b0 D
b0 C
b0 B
0A
b0 @
b0 ?
b0 >
b0 =
0<
b0 ;
b0 :
09
b0 8
17
b0 6
b0 5
b0 4
b0 3
b0 2
b0 1
10
b0 /
b0 .
0-
0,
0+
0*
0)
b0 (
b0 '
0&
b0 %
b0 $
0#
b0 "
0!
$end
#10000
b1000000000000000 6"
b1000000000000000 ;"
1&
#20000
0&
1)
#30000
1&
#40000
0&
1<
1-
#50000
1&
#60000
0&
#70000
1&
#80000
0&
#90000
1&
#100000
0&
b1 >
b1 7"
b1 %
b1 /
#110000
1&
#120000
0&
b1111110000010000 6
b1111110000010000 9"
b1111110000010000 (
b1111110000010000 2
#130000
1&
#140000
0&
b10 >
b10 7"
b10 %
b10 /
#150000
1&
#160000
0&
b1 6
b1 9"
b1 (
b1 2
#170000
1&
#180000
0&
b11 >
b11 7"
b11 %
b11 /
#190000
1&
#200000
0&
b1111010011010000 6
b1111010011010000 9"
b1111010011010000 (
b1111010011010000 2
#210000
1&
#220000
0&
b100 >
b100 7"
b100 %
b100 /
#230000
1&
#240000
0&
b1010 6
b1010 9"
b1010 (
b1010 2
#250000
1&
#260000
0&
b101 >
b101 7"
b101 %
b101 /
#270000
1&
#280000
0&
b1110001100000001 6
b1110001100000001 9"
b1110001100000001 (
b1110001100000001 2
#290000
1&
#300000
0&
b110 >
b110 7"
b110 %
b110 /
#310000
1&
#320000
0&
b1 6
b1 9"
b1 (
b1 2
#330000
1&
#340000
0&
b111 >
b111 7"
b111 %
b111 /
#350000
1&
#360000
0&
b1111110000010000 6
b1111110000010000 9"
b1111110000010000 (
b1111110000010000 2
#370000
1&
#380000
0&
b1000 >
b1000 7"
b1000 %
b1000 /
#390000
1&
#400000
0&
b1100 6
b1100 9"
b1100 (
b1100 2
#410000
1&
#420000
0&
b1001 >
b1001 7"
b1001 %
b1001 /
#430000
1&
#440000
0&
b1110101010000111 6
b1110101010000111 9"
b1110101010000111 (
b1110101010000111 2
#450000
1&
#460000
0&
b1010 >
b1010 7"
b1010 %
b1010 /
#470000
1&
#480000
0&
b0 6
b0 9"
b0 (
b0 2
#490000
1&
#500000
0&
b1011 >
b1011 7"
b1011 %
b1011 /
#510000
1&
#520000
0&
b1111110000010000 6
b1111110000010000 9"
b1111110000010000 (
b1111110000010000 2
#530000
1&
#540000
0&
b1100 >
b1100 7"
b1100 %
b1100 /
#550000
1&
#560000
0&
b10 6
b10 9"
b10 (
b10 2
#570000
1&
#580000
0&
b1101 >
b1101 7"
b1101 %
b1101 /
#590000
1&
#600000
0&
b1110001100001000 6
b1110001100001000 9"
b1110001100001000 (
b1110001100001000 2
#610000
1&
#620000
0&
b1110 >
b1110 7"
b1110 %
b1110 /
#630000
1&
#640000
0&
b1110 6
b1110 9"
b1110 (
b1110 2
#650000
1&
#660000
0&
b1111 >
b1111 7"
b1111 %
b1111 /
#670000
1&
#680000
0&
b1110101010000111 6
b1110101010000111 9"
b1110101010000111 (
b1110101010000111 2
#690000
1&
#700000
0&
0<
0-
#710000
1&
#720000
0&
1A
1,
#730000
1&
#740000
0&
#750000
1&
#760000
0&
b1110 C
b1110 4"
b1110 '
b1110 1
#770000
1&
#780000
0&
b1 @
b1 2"
b1 $
b1 .
#790000
b1110 4
b1110 J
b1110 "
b1110 3
b1110 B
b1110 5"
1&
#800000
0&
b10100 C
b10100 4"
b10100 '
b10100 1
#810000
1&
#820000
0&
0A
b0 @
b0 2"
b0 C
b0 4"
0,
#830000
1&
#840000
0&
1+
#850000
b1 5
b1 8"
b1 :
b1 k
b1 j
b1 1"
1E
1&
#860000
0&
#870000
1I
1h
0i
1x
1)"
b1110 C
b1110 4"
b1110 y
b1110 ;
b1110 g
b1110 p
b1110 +"
b1110 ."
b1111111111110001 w
b1110 *"
b1110 {
b1110 ""
b1111111111110001 }
b1110 #"
0F
b1110 q
b1110 |
1L
0N
1H
1e
1U
b1101 '"
b1111111111111111 $"
b1110 n
b1110 ,"
1~
1u
b1111110000010000 8
b1111110000010000 O
b1111110000010000 =
b1111110000010000 :"
0E
1&
#880000
0&
#890000
b10 5
b10 8"
b10 :
b10 k
b1110 r
b1110 &"
b1110 /"
b10 j
b10 1"
1E
1&
#900000
0&
#910000
0I
0h
1i
0x
0c
0)"
b0 C
b0 4"
b0 ""
b1111111111111111 }
b0 y
b0 ;
b0 g
b0 p
b0 +"
b0 ."
b1111111111111111 w
b0 #"
b0 *"
1F
b0 q
b0 |
0L
0^
1[
b1111111111110001 z
b0 {
1N
0H
0e
b1 n
b1 ,"
0V
0U
1S
1Z
b1110 %"
b1110 '"
b1110 $"
0~
0u
b1 8
b1 O
b1 =
b1 :"
0E
1&
#920000
0&
#930000
b1111 '"
b1 ""
b1111111111111110 }
b1 ?
b1 3"
b1 @
b1 2"
b1 #"
b1 D
b1 m
b1 q
b1 |
b11 5
b11 8"
b11 :
b11 k
b1 o
b1 -"
b1 0"
b11 j
b11 1"
1E
1&
#940000
0&
