UART/uart_rx.v
`default_nettype none

// Module for RX comm.
module uart_rx #(
	// Max. size of register
	parameter RATIO_REG_SIZE = 8,
	parameter DATA_BITS = 8
	)(
	input wire			clk,
	input wire			reset_n,
	input wire [RATIO_REG_SIZE - 1:0]	ratio,
	
	input wire			rx_enb,
	output reg			busy,
	output reg			new_data,
	output reg [DATA_BITS - 1:0]	data,
	
	input wire			parity_en,	// 1 to enable parity bit
	input wire			parity_odd,	// 0 for odd parity; 1 for even parity;
	output reg			parity_err,	// 1 for error in parity
	
	input wire			UART_RX
	);

	reg [RATIO_REG_SIZE - 1:0] 			prescaler;
	reg [RATIO_REG_SIZE - 1:0] 			ratio_reg;
	reg [($clog2(DATA_BITS + 2)) - 1:0]	index;
	reg [DATA_BITS + 2:0]			data_reg;	// start bit + data + parity + stop bit
	
	reg [1:0] curr_wrk;
	localparam [1:0]
		idle = 2'b00,
		data_rx = 2'b01,
		verify_st = 2'b10;
		
	initial
	begin
		curr_wrk = idle;
	end
	
	always @(posedge clk, posedge reset_n)
	begin
		if (~reset_n)
		begin
			prescaler <= {RATIO_REG_SIZE{1'b0}};
			ratio_reg <= {RATIO_REG_SIZE{1'b0}};
			data_reg <= {(DATA_BITS + 3){1'b0}};
			index <= {($clog2(DATA_BITS + 2)){1'b0}};
			busy <= 1'b0;
			new_data <= 1'b0;
			data = {DATA_BITS{1'b0}};
			parity_err = 1'b0;
			curr_wrk <= idle;
		end
		else
		begin
			case(curr_wrk)
				idle:
				begin
					prescaler <= {RATIO_REG_SIZE{1'b0}};
					ratio_reg <= {RATIO_REG_SIZE{1'b0}};
					data_reg <= {(DATA_BITS + 3){1'b0}};
					index <= {($clog2(DATA_BITS + 2)){1'b0}};
					busy <= 1'b0;
					new_data <= 1'b0;
					//data = {DATA_BITS{1'b0}};
					parity_err = 1'b0;
					if ((~UART_RX) & (rx_enb))
					begin
						ratio_reg <= ratio;
						busy <= 1'b1;
						curr_wrk <= data_rx;
					end
				end
				
				data_rx:
				begin
					if (prescaler < (ratio_reg - 1))
						prescaler <= prescaler + 1;
					else
						prescaler <= 1'b0;
					if (prescaler == (ratio_reg >> 1))
					begin
						if (index < (DATA_BITS + 3))
						begin
							data_reg[index] <= UART_RX;
							index <= index + 1;
							if ((~parity_en) & (index == DATA_BITS + 1))
							begin
								if (UART_RX)
									curr_wrk <= verify_st;
								else
									curr_wrk <= idle;
							end
						end
						else
						begin
							if (UART_RX)
								curr_wrk <= verify_st;
							else
								curr_wrk <= idle;
						end
					end
				end
				
				verify_st:
				begin
					data <= data_reg[DATA_BITS:1];
					if (parity_en)
					begin
						if (parity_odd)
							parity_err = (data_reg[DATA_BITS + 1] == ~(^data_reg[DATA_BITS:1])) ? 1'b0 : 1'b1 ;
						else
							parity_err = (data_reg[DATA_BITS + 1] == (^data_reg[DATA_BITS:1])) ? 1'b0 : 1'b1 ;
					end
					new_data <= 1'b1;
					curr_wrk <= idle;
				end
				
				default:
					curr_wrk <= idle;
			endcase
		end
	end

endmodule

`default_nettype wire

UART/uart_tx.v
`default_nettype none

// Module for TX comm.
module uart_tx #(
	// Max. size of register
	parameter RATIO_REG_SIZE = 8,
	parameter DATA_BITS = 8
	)(
	input wire			clk,
	input wire			reset_n,
	input wire [RATIO_REG_SIZE - 1:0]	ratio,
	
	input wire			tx_enb,
	output reg			busy,
	output reg			done,
	input wire [DATA_BITS - 1:0]	data,
	
	input wire			parity_en,	// 1 to enable parity bit
	input wire			parity_odd,	// 0 for odd parity; 1 for even parity;
	
	output reg			UART_TX
	);

	reg [RATIO_REG_SIZE - 1:0] 			prescaler;
	reg [RATIO_REG_SIZE - 1:0] 			ratio_reg;
	reg [($clog2(DATA_BITS + 2)) - 1:0]	index;
	reg [DATA_BITS + 2:0]			data_reg;	// start bit + data + parity + stop bit
	
	reg [1:0] curr_wrk;
	localparam
		idle = 1'b0,
		data_tx = 1'b1;
		
	initial
	begin
		curr_wrk = idle;
	end
	
	always @(posedge clk, posedge reset_n)
	begin
		if (~reset_n)
		begin
			prescaler <= {RATIO_REG_SIZE{1'b0}};
			ratio_reg <= {RATIO_REG_SIZE{1'b0}};
			data_reg <= {(DATA_BITS + 3){1'b0}};
			index <= {($clog2(DATA_BITS + 2)){1'b0}};
			busy <= 1'b0;
			done <= 1'b0;
			UART_TX <= 1'b1;
			curr_wrk <= idle;
		end
		else
		begin
			case(curr_wrk)
				idle:
				begin
					prescaler <= {RATIO_REG_SIZE{1'b0}};
					ratio_reg <= {RATIO_REG_SIZE{1'b0}};
					data_reg <= {(DATA_BITS + 3){1'b0}};
					index <= {($clog2(DATA_BITS + 2)){1'b0}};
					busy <= 1'b0;
					done <= 1'b0;
					UART_TX <= 1'b1;
					if (tx_enb)
					begin
						ratio_reg <= ratio;
						data_reg[0] <= 1'b0;	// Start bit
						data_reg[DATA_BITS:1] <= data;
						data_reg[DATA_BITS + 2] <= 1'b1;	// Stop bit
						if (parity_en)
						begin
							if (parity_odd)
								data_reg[DATA_BITS + 1] <= ~(^data);
							else
								data_reg[DATA_BITS + 1] <= ^data;
						end
						else
						data_reg[DATA_BITS + 1] <= 1'b1;	// Stop bit
						
						busy <= 1'b1;
						curr_wrk <= data_tx;
					end
				end
				
				data_tx:
				begin
					if (prescaler < (ratio_reg - 1))
						prescaler <= prescaler + 1;
					else
						prescaler <= 1'b0;
					if (prescaler == (ratio_reg >> 1))
					begin
						if (index < (DATA_BITS + 3))
						begin
							UART_TX <= data_reg[index];
							index <= index + 1;
							if ((~parity_en) & (index == DATA_BITS + 1)) begin
								done <= 1'b1;
								curr_wrk <= idle;
							end
						end
						else
						begin
							done <= 1'b1;
							curr_wrk <= idle;
						end
					end
				end
			
			endcase
		end
	end

endmodule

`default_nettype wire

UART/Fifo.v
/////////////////////////////////////////////////////////
// This module is to create a Fifo inside the project. //
// The Fifo's data size and depth can be adjusted      //
// using the parameters, "DATA_SIZE" and "FIFO_SIZE"   //
// respectively.                                       //
/////////////////////////////////////////////////////////

`default_nettype none

// Main module for Fifo
module Fifo#(
	parameter DATA_SIZE = 8,
	parameter FIFO_SIZE = 8	// Fifo size
	)(
	// Power pins
	`ifdef USE_POWER_PINS
	inout vccd1,			// User area 1 1.8V supply
	inout vssd1,			// User area 1 digital ground
	`endif
	// Ports
	input wire clock,		// Main clk for fifo
	input wire reset_n,		// Master reset for fifo
	
	input wire data_inen,		// Data in flag
	input wire data_outen,		// Data out flag
	
	output wire fifo_empty,	// Fifo empty flag
	output wire fifo_full,		// Fifo full flag
	
	input wire [(DATA_SIZE-1):0] data_in,	// Data input to fifo
	output reg [(DATA_SIZE-1):0] data_out	// Data output from fifo
	);
	
	reg [($clog2(FIFO_SIZE) - 1) : 0] wptr;	// Write pointer
	reg [($clog2(FIFO_SIZE) - 1) : 0] rptr;	// Read pointer
	
	reg fifo_emptyreg;				// Fifo empty reg
	reg fifo_fullreg;				// Fifo full reg
	
	reg [(DATA_SIZE-1):0] memory [(FIFO_SIZE - 1):0];	// Memory for the fifo
	
	integer i = 0;					// temp variable
	
	assign fifo_empty = fifo_emptyreg;
	assign fifo_full = fifo_fullreg;
	
	initial begin
		wptr = 0;
		rptr = 0;
		
		fifo_emptyreg = 1'b1;
		fifo_fullreg  = 1'b0;
		
		data_out = {DATA_SIZE{1'b0}};
		
		for (i=0; i<FIFO_SIZE; i=i+1)
			memory[i] = 0;
	end
	
	always @ (posedge clock, negedge reset_n) begin
		if (~reset_n) begin	// reset everything
			wptr = 0;
			rptr = 0;
			
			fifo_emptyreg = 1'b1;
			fifo_fullreg  = 1'b0;
			
			data_out = {DATA_SIZE{1'b0}};
			
			for (i=0; i<FIFO_SIZE; i=i+1)
				memory[i] = 0;
		end
		else begin
			if ((~fifo_fullreg) & (data_inen)) begin
				memory[wptr] <= data_in;
				wptr <= wptr + 1;
				fifo_emptyreg <= 1'b0;
				
				if ((wptr+1'b1)==rptr)
					fifo_fullreg <= 1'b1;
				else
					fifo_fullreg <= 1'b0;
			end
			
			if ((~fifo_emptyreg) & (data_outen)) begin
				data_out <= memory[rptr];
				rptr <= rptr + 1;
				fifo_fullreg <= 1'b0;
				
				if ((rptr+1'b1)==wptr)
					fifo_emptyreg <= 1'b1;
				else
					fifo_emptyreg <= 1'b0;
			end
		end
	end

endmodule

`default_nettype wire

UART/UART_cntrl.v
/////////////////////////////////////////////////////////
// This module is to create a upper level control of   //
// the UART module. It is used to set the parameters   //
// of the module and also to attach the FIFO to it.    //
// FIFO is used to collect the data from user and to   //
// save it before forwarding to the UART. Similarly,   //
// another FIFO is used to save data from UART before  //
// forwarding to user.                                 //
/////////////////////////////////////////////////////////

`default_nettype none

// Main module for the UART_cntrl
module UART_cntrl (
	input	wire		clock,		// Main clock for module
	input	wire		reset_n,	// System reset
	
	input	wire		start_tx,	// Start the UART-Tx
	input	wire		start_rx,	// Start the UART-Rx
	input	wire [7:0]	clk_ratio,	// Ratio of clock to baudrate
	
	input	wire		fifo_wren,	// Fifo write en
	input	wire		fifo_rden,	// Fifo read en
	input	wire [7:0]	data_in,	// Data to the fifo
	output	wire [7:0]	data_out,	// Data from the fifo
	
	input wire		parityen,	// 1 to enable parity bit
	input wire		parityodd,	// 0 for odd parity; 1 for even parity;
	
	output reg		busy_tx,	// UART_Tx working signal
	output reg		busy_rx,	// UART_Rx working signal
	
	output wire		data_fulltx,	// Tx fifo full flag
	output wire		data_emptytx,	// Tx fifo empty flag
	
	output wire		data_fullrx,	// Rx fifo full flag
	output wire		data_emptyrx,	// Rx fifo empty flag
	// External ports
	output	wire		UART_Tx,	// UART Transmission port
	input	wire		UART_Rx	// UART Receiving port
	);
	
	wire fifo_fulltx;
	wire fifo_emptytx;
	
	wire fifo_fullrx;
	wire fifo_emptyrx;
	
	reg dataen_tx;
	reg tx_start;
	wire busytx;
	wire done_tx;
	reg prty_entx;
	reg prty_oddtx;
	wire [7:0] data_tx;
	
	reg dataen_rx;
	wire parity_err;
	reg rx_start;
	wire busyrx;
	wire done_rx;
	reg prty_enrx;
	reg prty_oddrx;
	wire [7:0] data_rx;
	reg [7:0] data_rxfifo;
	
	reg [1:0] curr_tx, curr_rx;
	localparam [1:0]
		idle_st	= 2'b00,
		read_st	= 2'b01,
		write_st	= 2'b10,
		stop_st	= 2'b11;
	
	Fifo #(.DATA_SIZE(8), .FIFO_SIZE(8))
	Fifo_tx (.clock(clock), .reset_n(reset_n),
	        .data_inen(fifo_wren), .data_outen(dataen_tx),
	        .fifo_empty(fifo_emptytx), .fifo_full(fifo_fulltx),
	        .data_in(data_in), .data_out(data_tx));
	       
	Fifo #(.DATA_SIZE(8), .FIFO_SIZE(8))
	Fifo_rx (.clock(clock), .reset_n(reset_n),
	        .data_inen(dataen_rx), .data_outen(fifo_rden),
	        .fifo_empty(fifo_emptyrx), .fifo_full(fifo_fullrx),
	        .data_in(data_rxfifo), .data_out(data_out));
	
	uart_tx #(.RATIO_REG_SIZE(8), .DATA_BITS(8))
	tx0	 (.clk(clock), .reset_n(reset_n), .ratio(clk_ratio),
		  .tx_enb(tx_start), .busy(busytx), .done(done_tx),
		  .data(data_tx), .parity_en(prty_entx), .parity_odd(prty_oddtx),
		  .UART_TX(UART_Tx));
	
	uart_rx #(.RATIO_REG_SIZE(8), .DATA_BITS(8))
	rx0	 (.clk(clock), .reset_n(reset_n), .ratio(clk_ratio),
		  .rx_enb(rx_start), .busy(busyrx), .new_data(done_rx),
		  .data(data_rx), .parity_en(prty_enrx), .parity_odd(prty_oddrx),
		  .parity_err(parity_err), .UART_RX(UART_Rx));
	
	assign data_fulltx = fifo_fulltx;
	assign data_emptytx = fifo_emptytx;
	
	assign data_fullrx = fifo_fullrx;
	assign data_emptyrx = fifo_emptyrx;
	
	initial begin
		busy_tx = 1'b0;
		busy_rx = 1'b0;
		dataen_tx = 1'b0;
		tx_start = 1'b0;
		prty_entx = 1'b0;
		prty_oddtx = 1'b0;
		dataen_rx = 1'b0;
		rx_start = 1'b0;
		prty_enrx = 1'b0;
		prty_oddrx = 1'b0;
		curr_tx = 2'b00;
		curr_rx = 2'b00;
		data_rxfifo = 8'd0;
	end
	
	always @(posedge clock , negedge reset_n) begin
		if (~reset_n) begin
			curr_tx = 2'b00;
			curr_rx = 2'b00;	
		end
		else begin
			case(curr_tx)
				idle_st: begin
					busy_tx	<= 1'b0;
					dataen_tx	<= 1'b0;
					tx_start	<= 1'b0;
					prty_entx	<= 1'b0;
					prty_oddtx	<= 1'b0;
					if ((start_tx) && (~fifo_emptytx)) begin
						prty_entx <= parityen;
						prty_oddtx <= parityodd;
						busy_tx <= 1'b1;
						curr_tx <= read_st;
					end
				end
				
				read_st: begin
					if (~busytx) begin
						dataen_tx <= 1'b1;
						curr_tx <= write_st;
					end
				end
				
				write_st: begin
					dataen_tx <= 1'b0;
					tx_start <= 1'b1;
					curr_tx <= stop_st;
				end
				
				stop_st: begin
					dataen_tx <= 1'b0;
					tx_start <= 1'b0;
					if (done_tx) begin
						if (fifo_emptytx)
							curr_tx <= idle_st;
						else
							curr_tx <= read_st;
					end
				end
			endcase
			case(curr_rx)
				idle_st: begin
					busy_rx	<= 1'b0;
					dataen_rx	<= 1'b0;
					rx_start	<= 1'b0;
					prty_enrx	<= 1'b0;
					prty_oddrx	<= 1'b0;
					data_rxfifo	<= 8'd0;
					if ((start_rx) && (~fifo_fullrx)) begin
						prty_enrx <= parityen;
						prty_oddrx <= parityodd;
						rx_start <= 1'b1;
						curr_rx <= read_st;
					end
				end
				
				read_st: begin
					if ((busyrx) && (done_rx)) begin
						if (~parity_err) begin
							dataen_rx <= 1'b1;
							data_rxfifo <= data_rx;
						end
						curr_rx <= write_st;
					end
					if (busyrx)
						busy_rx <= 1'b1;
					else
						busy_rx <= 1'b0;
				end
				
				write_st: begin
					dataen_rx <= 1'b0;
					busy_rx <= 1'b0;
					curr_rx <= stop_st;
				end
				
				stop_st: begin
					if ((start_rx) && (~fifo_fullrx))
						curr_rx <= read_st;
					else
						curr_rx <= idle_st;
				end
			endcase
		end
	end
	
endmodule

`default_nettype wire

UART/UART_cntrl_tb.v
/////////////////////////////////////////////////////////
// This module is to test the UART_cntrl project. For  //
// more details, please refer "UART_cntrl.v" design.   //
/////////////////////////////////////////////////////////

`default_nettype none

`timescale 10 ns / 1 ps

module UART_cntrl_tb();
	reg	clock;		// Main clock for module
	reg	reset_n;	// System reset
	
	reg	start_tx;	// Start the UART-Tx
	reg	start_rx;	// Start the UART-Rx
	reg [7:0] clk_ratio;	// Ratio of clock to baudrate
	
	reg	fifo_wren;	// Fifo write en
	reg	fifo_rden;	// Fifo read en
	reg [7:0] data_in;	// Data to the fifo
	wire [7:0] data_out;	// Data from the fifo
	
	reg	parityen;	// 1 to enable parity bit
	reg	parityodd;	// 0 for odd parity; 1 for even parity;
	
	wire	busy_tx;	// UART_Tx working signal
	wire	busy_rx;	// UART_Rx working signal
	
	wire	data_fulltx;	// Tx fifo full flag
	wire	data_emptytx;	// Tx fifo empty flag
	
	wire	data_fullrx;	// Rx fifo full flag
	wire	data_emptyrx;	// Rx fifo empty flag
	// External ports
	wire	UART_Tx;	// Serial Interface Enable; Active low
	reg	UART_Rx;	// Serial Interface Clock
	
	reg [7:0] check_reg_tb0;
	reg [7:0] check_reg_tb1;
	reg [7:0] check_reg_tb2;
	
	UART_cntrl UART0 (.clock(clock), .reset_n(reset_n),
			  .start_tx(start_tx), .start_rx(start_rx), .clk_ratio(clk_ratio),
			  .fifo_wren(fifo_wren), .fifo_rden(fifo_rden),
			  .data_in(data_in), .data_out(data_out),
			  .parityen(parityen), .parityodd(parityodd),
			  .busy_tx(busy_tx), .busy_rx(busy_rx),
			  .data_fulltx(data_fulltx), .data_emptytx(data_emptytx),
			  .data_fullrx(data_fullrx), .data_emptyrx(data_emptyrx),
			  .UART_Tx(UART_Tx), .UART_Rx(UART_Rx));
	
	initial begin
		clock		= 1'b0;
		reset_n	= 1'b0;
		start_tx	= 1'b0;
		start_rx	= 1'b0;
		
		fifo_wren	= 1'b0;
		fifo_rden	= 1'b0;
		
		parityen	= 1'b0;
		parityodd	= 1'b0;
		
		UART_Rx	= 1'b0;
		
		clk_ratio	= 8'd0;
		data_in	= 8'd0;
	end
	
	always #1 clock <= ~clock;
	
	always @(posedge clock) UART_Rx <= UART_Tx;
	
	initial begin
		// Starting setup
		#10 reset_n	= 1'b1;
		#2 clk_ratio	= 8'd8;
		parityen	= 1'b1;
		parityodd	= 1'b1;
		#2 data_in	= 8'ha5;
		fifo_wren	= 1'b1;
		#2 data_in	= 8'h21;
		#2 data_in	= 8'h3d;
		#2 fifo_wren	= 1'b0;
		// Starting Tx and Rx
		#2 start_rx	= 1'b1;
		start_tx	= 1'b1;
		#800 start_tx = 1'b0;
		start_rx	= 1'b0;
		// Starting validation
		#2 fifo_rden	= 1'b1;
		#2 check_reg_tb0 = data_out;
		#2 check_reg_tb1 = data_out;
		#2 check_reg_tb2 = data_out;
		#2 fifo_rden	= 1'b0;
		$display("check_reg_tb0 : ", check_reg_tb0);
		$display("check_reg_tb1 : ", check_reg_tb1);
		$display("check_reg_tb2 : ", check_reg_tb2);
		if ((check_reg_tb0 == 8'ha5) &&
		    (check_reg_tb1 == 8'h21) &&
		    (check_reg_tb2 == 8'h3d))
			$display("All Test casses passed!!!");
		else
			$display("Test Failed...");
		$finish;
	end
	
	initial begin
		$dumpfile("UART_cntrl_tb.vcd");
		$dumpvars(0, UART_cntrl_tb);
		
		repeat(1000) @(posedge clock);
		$display("Monitor: Timeout; Test failed...");
		$finish;
	end
	
endmodule

`default_nettype wire

UART/UART_cntrl_tb.vcd
$date
	Wed Dec 28 00:24:36 2022
$end
$version
	Icarus Verilog
$end
$timescale
	1ps
$end
$scope module UART_cntrl_tb $end
$var wire 8 ! data_out [7:0] $end
$var wire 1 " data_fulltx $end
$var wire 1 # data_fullrx $end
$var wire 1 $ data_emptytx $end
$var wire 1 % data_emptyrx $end
$var wire 1 & busy_tx $end
$var wire 1 ' busy_rx $end
$var wire 1 ( UART_Tx $end
$var reg 1 ) UART_Rx $end
$var reg 8 * check_reg_tb0 [7:0] $end
$var reg 8 + check_reg_tb1 [7:0] $end
$var reg 8 , check_reg_tb2 [7:0] $end
$var reg 8 - clk_ratio [7:0] $end
$var reg 1 . clock $end
$var reg 8 / data_in [7:0] $end
$var reg 1 0 fifo_rden $end
$var reg 1 1 fifo_wren $end
$var reg 1 2 parityen $end
$var reg 1 3 parityodd $end
$var reg 1 4 reset_n $end
$var reg 1 5 start_rx $end
$var reg 1 6 start_tx $end
$scope module UART0 $end
$var wire 1 ) UART_Rx $end
$var wire 8 7 clk_ratio [7:0] $end
$var wire 1 . clock $end
$var wire 1 % data_emptyrx $end
$var wire 1 $ data_emptytx $end
$var wire 1 # data_fullrx $end
$var wire 1 " data_fulltx $end
$var wire 8 8 data_in [7:0] $end
$var wire 1 0 fifo_rden $end
$var wire 1 1 fifo_wren $end
$var wire 1 2 parityen $end
$var wire 1 3 parityodd $end
$var wire 1 4 reset_n $end
$var wire 1 5 start_rx $end
$var wire 1 6 start_tx $end
$var wire 1 9 parity_err $end
$var wire 1 : fifo_fulltx $end
$var wire 1 ; fifo_fullrx $end
$var wire 1 < fifo_emptytx $end
$var wire 1 = fifo_emptyrx $end
$var wire 1 > done_tx $end
$var wire 1 ? done_rx $end
$var wire 8 @ data_tx [7:0] $end
$var wire 8 A data_rx [7:0] $end
$var wire 8 B data_out [7:0] $end
$var wire 1 C busytx $end
$var wire 1 D busyrx $end
$var wire 1 ( UART_Tx $end
$var reg 1 ' busy_rx $end
$var reg 1 & busy_tx $end
$var reg 2 E curr_rx [1:0] $end
$var reg 2 F curr_tx [1:0] $end
$var reg 8 G data_rxfifo [7:0] $end
$var reg 1 H dataen_rx $end
$var reg 1 I dataen_tx $end
$var reg 1 J prty_enrx $end
$var reg 1 K prty_entx $end
$var reg 1 L prty_oddrx $end
$var reg 1 M prty_oddtx $end
$var reg 1 N rx_start $end
$var reg 1 O tx_start $end
$scope module Fifo_rx $end
$var wire 1 . clock $end
$var wire 8 P data_in [7:0] $end
$var wire 1 H data_inen $end
$var wire 1 0 data_outen $end
$var wire 1 4 reset_n $end
$var wire 1 ; fifo_full $end
$var wire 1 = fifo_empty $end
$var reg 8 Q data_out [7:0] $end
$var reg 1 = fifo_emptyreg $end
$var reg 1 ; fifo_fullreg $end
$var reg 3 R rptr [2:0] $end
$var reg 3 S wptr [2:0] $end
$var integer 32 T i [31:0] $end
$upscope $end
$scope module Fifo_tx $end
$var wire 1 . clock $end
$var wire 8 U data_in [7:0] $end
$var wire 1 1 data_inen $end
$var wire 1 I data_outen $end
$var wire 1 4 reset_n $end
$var wire 1 : fifo_full $end
$var wire 1 < fifo_empty $end
$var reg 8 V data_out [7:0] $end
$var reg 1 < fifo_emptyreg $end
$var reg 1 : fifo_fullreg $end
$var reg 3 W rptr [2:0] $end
$var reg 3 X wptr [2:0] $end
$var integer 32 Y i [31:0] $end
$upscope $end
$scope module rx0 $end
$var wire 1 ) UART_RX $end
$var wire 1 . clk $end
$var wire 1 J parity_en $end
$var wire 1 L parity_odd $end
$var wire 8 Z ratio [7:0] $end
$var wire 1 4 reset_n $end
$var wire 1 N rx_enb $end
$var reg 1 D busy $end
$var reg 2 [ curr_wrk [1:0] $end
$var reg 8 \ data [7:0] $end
$var reg 11 ] data_reg [10:0] $end
$var reg 4 ^ index [3:0] $end
$var reg 1 ? new_data $end
$var reg 1 9 parity_err $end
$var reg 8 _ prescaler [7:0] $end
$var reg 8 ` ratio_reg [7:0] $end
$upscope $end
$scope module tx0 $end
$var wire 1 . clk $end
$var wire 8 a data [7:0] $end
$var wire 1 K parity_en $end
$var wire 1 M parity_odd $end
$var wire 8 b ratio [7:0] $end
$var wire 1 4 reset_n $end
$var wire 1 O tx_enb $end
$var reg 1 ( UART_TX $end
$var reg 1 C busy $end
$var reg 2 c curr_wrk [1:0] $end
$var reg 11 d data_reg [10:0] $end
$var reg 1 > done $end
$var reg 4 e index [3:0] $end
$var reg 8 f prescaler [7:0] $end
$var reg 8 g ratio_reg [7:0] $end
$upscope $end
$upscope $end
$upscope $end
$enddefinitions $end
#0
$dumpvars
bx g
bx f
bx e
bx d
b0 c
b0 b
b0 a
bx `
bx _
bx ^
bx ]
bx \
b0 [
b0 Z
b1000 Y
b0 X
b0 W
b0 V
b0 U
b1000 T
b0 S
b0 R
b0 Q
b0 P
0O
0N
0M
0L
0K
0J
0I
0H
b0 G
b0 F
b0 E
xD
xC
b0 B
bx A
b0 @
x?
x>
1=
1<
0;
0:
x9
b0 8
b0 7
06
05
04
03
02
01
00
b0 /
0.
b0 -
bx ,
bx +
bx *
0)
x(
0'
0&
1%
1$
0#
0"
b0 !
$end
#10000
1(
0>
0C
b0 e
b0 d
b0 g
b0 f
0?
0D
b0 ^
b0 ]
b0 `
b0 _
x)
b1000 T
b1000 Y
09
b0 A
b0 \
1.
#20000
0.
#30000
1)
b1000 Y
b1000 T
1.
#40000
0.
#50000
b1000 T
b1000 Y
1.
#60000
0.
#70000
b1000 Y
b1000 T
1.
#80000
0.
#90000
b1000 T
b1000 Y
1.
#100000
0.
14
#110000
1.
#120000
0.
13
12
b1000 -
b1000 7
b1000 Z
b1000 b
#130000
1.
#140000
0.
11
b10100101 /
b10100101 8
b10100101 U
#150000
0$
0<
b1 X
1.
#160000
0.
b100001 /
b100001 8
b100001 U
#170000
b10 X
1.
#180000
0.
b111101 /
b111101 8
b111101 U
#190000
b11 X
1.
#200000
0.
01
#210000
1.
#220000
0.
16
15
#230000
b1 E
1N
1L
1J
b1 F
1&
1M
1K
1.
#240000
0.
#250000
b10 F
1I
1.
#260000
0.
#270000
b1 W
b10100101 @
b10100101 V
b10100101 a
b11 F
1O
0I
1.
#280000
0.
#290000
0O
b1 c
1C
b11101001010 d
b1000 g
1.
#300000
0.
#310000
b1 f
1.
#320000
0.
#330000
b10 f
1.
#340000
0.
#350000
b11 f
1.
#360000
0.
#370000
b100 f
1.
#380000
0.
#390000
b1 e
0(
b101 f
1.
#400000
0.
#410000
b110 f
0)
1.
#420000
0.
#430000
b111 f
b1 [
1D
b1000 `
1.
#440000
0.
#450000
1'
b1 _
b0 f
1.
#460000
0.
#470000
b1 f
b10 _
1.
#480000
0.
#490000
b11 _
b10 f
1.
#500000
0.
#510000
b11 f
b100 _
1.
#520000
0.
#530000
b1 ^
b101 _
b100 f
1.
#540000
0.
#550000
b10 e
1(
b101 f
b110 _
1.
#560000
0.
#570000
b111 _
b110 f
1)
1.
#580000
0.
#590000
b111 f
b0 _
1.
#600000
0.
#610000
b1 _
b0 f
1.
#620000
0.
#630000
b1 f
b10 _
1.
#640000
0.
#650000
b11 _
b10 f
1.
#660000
0.
#670000
b11 f
b100 _
1.
#680000
0.
#690000
b10 ^
b10 ]
b101 _
b100 f
1.
#700000
0.
#710000
b11 e
0(
b101 f
b110 _
1.
#720000
0.
#730000
b111 _
b110 f
0)
1.
#740000
0.
#750000
b111 f
b0 _
1.
#760000
0.
#770000
b1 _
b0 f
1.
#780000
0.
#790000
b1 f
b10 _
1.
#800000
0.
#810000
b11 _
b10 f
1.
#820000
0.
#830000
b11 f
b100 _
1.
#840000
0.
#850000
b11 ^
b101 _
b100 f
1.
#860000
0.
#870000
b100 e
1(
b101 f
b110 _
1.
#880000
0.
#890000
b111 _
b110 f
1)
1.
#900000
0.
#910000
b111 f
b0 _
1.
#920000
0.
#930000
b1 _
b0 f
1.
#940000
0.
#950000
b1 f
b10 _
1.
#960000
0.
#970000
b11 _
b10 f
1.
#980000
0.
#990000
b11 f
b100 _
1.
#1000000
0.
#1010000
b100 ^
b1010 ]
b101 _
b100 f
1.
#1020000
0.
#1030000
b101 e
0(
b101 f
b110 _
1.
#1040000
0.
#1050000
b111 _
b110 f
0)
1.
#1060000
0.
#1070000
b111 f
b0 _
1.
#1080000
0.
#1090000
b1 _
b0 f
1.
#1100000
0.
#1110000
b1 f
b10 _
1.
#1120000
0.
#1130000
b11 _
b10 f
1.
#1140000
0.
#1150000
b11 f
b100 _
1.
#1160000
0.
#1170000
b101 ^
b101 _
b100 f
1.
#1180000
0.
#1190000
b110 e
b101 f
b110 _
1.
#1200000
0.
#1210000
b111 _
b110 f
1.
#1220000
0.
#1230000
b111 f
b0 _
1.
#1240000
0.
#1250000
b1 _
b0 f
1.
#1260000
0.
#1270000
b1 f
b10 _
1.
#1280000
0.
#1290000
b11 _
b10 f
1.
#1300000
0.
#1310000
b11 f
b100 _
1.
#1320000
0.
#1330000
b110 ^
b101 _
b100 f
1.
#1340000
0.
#1350000
b111 e
1(
b101 f
b110 _
1.
#1360000
0.
#1370000
b111 _
b110 f
1)
1.
#1380000
0.
#1390000
b111 f
b0 _
1.
#1400000
0.
#1410000
b1 _
b0 f
1.
#1420000
0.
#1430000
b1 f
b10 _
1.
#1440000
0.
#1450000
b11 _
b10 f
1.
#1460000
0.
#1470000
b11 f
b100 _
1.
#1480000
0.
#1490000
b111 ^
b1001010 ]
b101 _
b100 f
1.
#1500000
0.
#1510000
b1000 e
0(
b101 f
b110 _
1.
#1520000
0.
#1530000
b111 _
b110 f
0)
1.
#1540000
0.
#1550000
b111 f
b0 _
1.
#1560000
0.
#1570000
b1 _
b0 f
1.
#1580000
0.
#1590000
b1 f
b10 _
1.
#1600000
0.
#1610000
b11 _
b10 f
1.
#1620000
0.
#1630000
b11 f
b100 _
1.
#1640000
0.
#1650000
b1000 ^
b101 _
b100 f
1.
#1660000
0.
#1670000
b1001 e
1(
b101 f
b110 _
1.
#1680000
0.
#1690000
b111 _
b110 f
1)
1.
#1700000
0.
#1710000
b111 f
b0 _
1.
#1720000
0.
#1730000
b1 _
b0 f
1.
#1740000
0.
#1750000
b1 f
b10 _
1.
#1760000
0.
#1770000
b11 _
b10 f
1.
#1780000
0.
#1790000
b11 f
b100 _
1.
#1800000
0.
#1810000
b1001 ^
b101001010 ]
b101 _
b100 f
1.
#1820000
0.
#1830000
b1010 e
b101 f
b110 _
1.
#1840000
0.
#1850000
b111 _
b110 f
1.
#1860000
0.
#1870000
b111 f
b0 _
1.
#1880000
0.
#1890000
b1 _
b0 f
1.
#1900000
0.
#1910000
b1 f
b10 _
1.
#1920000
0.
#1930000
b11 _
b10 f
1.
#1940000
0.
#1950000
b11 f
b100 _
1.
#1960000
0.
#1970000
b1010 ^
b1101001010 ]
b101 _
b100 f
1.
#1980000
0.
#1990000
b1011 e
b101 f
b110 _
1.
#2000000
0.
#2010000
b111 _
b110 f
1.
#2020000
0.
#2030000
b111 f
b0 _
1.
#2040000
0.
#2050000
b1 _
b0 f
1.
#2060000
0.
#2070000
b1 f
b10 _
1.
#2080000
0.
#2090000
b11 _
b10 f
1.
#2100000
0.
#2110000
b11 f
b100 _
1.
#2120000
0.
#2130000
b1011 ^
b11101001010 ]
b101 _
b100 f
1.
#2140000
0.
#2150000
b0 c
1>
b101 f
b110 _
1.
#2160000
0.
#2170000
b1 F
b111 _
0>
0C
b0 e
b0 d
b0 g
b0 f
1.
#2180000
0.
#2190000
b10 F
1I
b0 _
1.
#2200000
0.
#2210000
b11 F
1O
0I
b10 W
b100001 @
b100001 V
b100001 a
b1 _
1.
#2220000
0.
#2230000
0O
b1 c
1C
b11001000010 d
b1000 g
b10 _
1.
#2240000
0.
#2250000
b11 _
b1 f
1.
#2260000
0.
#2270000
b10 f
b100 _
1.
#2280000
0.
#2290000
b10 [
b101 _
b11 f
1.
#2300000
0.
#2310000
b100 f
b0 [
1?
b10100101 A
b10100101 \
1.
#2320000
0.
#2330000
b10 E
b10100101 G
b10100101 P
1H
0?
0D
b0 ^
b0 ]
b0 `
b0 _
b1 e
0(
b101 f
1.
#2340000
0.
